[
    {
     "url": "https://www2.yggtorrent.ws/torrent/audio/musique/363992-lomepal+-+jeannine+-+2018+mp3-320kbps",
     "name": "Lomepal - Jeannine - 2018 [MP3-320kbps]",
     "age": "1544109185",
     "size": "120.23Mo",
     "completed": "2910",
     "seed": "87",
     "leech": "1",
     "downloadurl": "https://www2.yggtorrent.ws//engine/download_torrent?id=363992"
    },
    {
     "url": "https://www2.yggtorrent.ws/torrent/audio/musique/517151-lomepal+-+amina+2019mp3320kbps",
     "name": "Lomepal - Amina [2019][MP3][320KBPS]",
     "age": "1571955245",
     "size": "223.87Mo",
     "completed": "1021",
     "seed": "66",
     "leech": "0",
     "downloadurl": "https://www2.yggtorrent.ws//engine/download_torrent?id=517151"
    },
    {
     "url": "https://www2.yggtorrent.ws/torrent/audio/musique/189598-lomepal+-+flip+deluxe+2017+mp3+-+320+kbps",
     "name": "Lomepal - Flip [Deluxe] [2017] [MP3 - 320 kbps]",
     "age": "1518797529",
     "size": "260.28Mo",
     "completed": "1272",
     "seed": "53",
     "leech": "0",
     "downloadurl": "https://www2.yggtorrent.ws//engine/download_torrent?id=189598"
    },
    {
     "url": "https://www2.yggtorrent.ws/torrent/audio/musique/517150-lomepal+-+amina+2019flac+16bit44100hz",
     "name": "Lomepal - Amina [2019][FLAC 16Bit][44100Hz]",
     "age": "1571954942",
     "size": "525.92Mo",
     "completed": "452",
     "seed": "34",
     "leech": "1",
     "downloadurl": "https://www2.yggtorrent.ws//engine/download_torrent?id=517150"
    },
    {
     "url": "https://www2.yggtorrent.ws/torrent/audio/musique/434633-lomepal+-+jeannine+2018flac+16bit44100hz",
     "name": "Lomepal - Jeannine [2018][FLAC 16Bit][44100Hz]",
     "age": "1554907698",
     "size": "318.57Mo",
     "completed": "652",
     "seed": "33",
     "leech": "0",
     "downloadurl": "https://www2.yggtorrent.ws//engine/download_torrent?id=434633"
    },
    {
     "url": "https://www2.yggtorrent.ws/torrent/audio/musique/515227-2019+lomepal+-+3+jours+à+motorbass+mp3+320kbps",
     "name": "[2019] Lomepal - 3 jours à Motorbass [MP3 320kbps]",
     "age": "1571510481",
     "size": "120.44Mo",
     "completed": "372",
     "seed": "30",
     "leech": "0",
     "downloadurl": "https://www2.yggtorrent.ws//engine/download_torrent?id=515227"
    },
    {
     "url": "https://www2.yggtorrent.ws/torrent/audio/musique/5377-lomepal+-+flip+2017+hi-res+24-44+1",
     "name": "Lomepal - FLIP (2017) [Hi-Res 24-44.1]",
     "age": "1499615714",
     "size": "694.76Mo",
     "completed": "306",
     "seed": "20",
     "leech": "0",
     "downloadurl": "https://www2.yggtorrent.ws//engine/download_torrent?id=5377"
    },
    {
     "url": "https://www2.yggtorrent.ws/torrent/audio/musique/373066-lomepal+-+cette+foutue+perle+2013flac+16bit44100hz",
     "name": "Lomepal - Cette Foutue Perle [2013][FLAC 16Bit][44100Hz]",
     "age": "1545307670",
     "size": "202.30Mo",
     "completed": "134",
     "seed": "15",
     "leech": "0",
     "downloadurl": "https://www2.yggtorrent.ws//engine/download_torrent?id=373066"
    },
    {
     "url": "https://www2.yggtorrent.ws/torrent/audio/musique/373068-lomepal+-+majesté+2015flac+16bit44100hz",
     "name": "Lomepal - Majesté [2015][FLAC 16Bit][44100Hz]",
     "age": "1545307674",
     "size": "218.88Mo",
     "completed": "187",
     "seed": "12",
     "leech": "0",
     "downloadurl": "https://www2.yggtorrent.ws//engine/download_torrent?id=373068"
    },
    {
     "url": "https://www2.yggtorrent.ws/torrent/audio/musique/173607-lomepal+-+odsl+2016+mp3+320kbps",
     "name": "Lomepal - ODSL (2016) MP3 320Kbps",
     "age": "1516989207",
     "size": "53.38Mo",
     "completed": "264",
     "seed": "11",
     "leech": "0",
     "downloadurl": "https://www2.yggtorrent.ws//engine/download_torrent?id=173607"
    },
    {
     "url": "https://www2.yggtorrent.ws/torrent/audio/musique/264722-lomepal+-+odsl+2016+flac+16bits+441khz",
     "name": "Lomepal - ODSL (2016) [FLAC 16bits 44,1kHz]",
     "age": "1529237019",
     "size": "128.50Mo",
     "completed": "107",
     "seed": "11",
     "leech": "0",
     "downloadurl": "https://www2.yggtorrent.ws//engine/download_torrent?id=264722"
    },
    {
     "url": "https://www2.yggtorrent.ws/torrent/filmvidéo/concert/515464-lomepal+-+3+jours+à+motorbass+arte+2019+webrip+1080i",
     "name": "Lomepal - 3 Jours à Motorbass (ARTE) 2019 WEBrip 1080i",
     "age": "1571573144",
     "size": "2.00Go",
     "completed": "102",
     "seed": "11",
     "leech": "0",
     "downloadurl": "https://www2.yggtorrent.ws//engine/download_torrent?id=515464"
    },
    {
     "url": "https://www2.yggtorrent.ws/torrent/audio/musique/373067-lomepal+-+seigneur+2014flac+16bit44100hz",
     "name": "Lomepal - Seigneur [2014][FLAC 16Bit][44100Hz]",
     "age": "1545307672",
     "size": "248.49Mo",
     "completed": "216",
     "seed": "10",
     "leech": "0",
     "downloadurl": "https://www2.yggtorrent.ws//engine/download_torrent?id=373067"
    },
    {
     "url": "https://www2.yggtorrent.ws/torrent/audio/musique/373159-lomepal+hologram+lo+caballero+-+le+singe+fume+sa+cigarette+2013flac+16bit44100hz",
     "name": "Lomepal / Hologram Lo' / Caballero - Le Singe Fume Sa Cigarette [2013][FLAC 16Bit][44100Hz]",
     "age": "1545317984",
     "size": "239.85Mo",
     "completed": "83",
     "seed": "8",
     "leech": "0",
     "downloadurl": "https://www2.yggtorrent.ws//engine/download_torrent?id=373159"
    },
    {
     "url": "https://www2.yggtorrent.ws/torrent/audio/musique/223165-hip-hop+rap+fr+caballero+lomepal+hologram+lo+-+le+singe+fume+sa+cigarette+2013+mp3+320kbps",
     "name": "[Hip-Hop, Rap FR] Caballero, Lomepal & Hologram Lo' - Le singe fume sa cigarette (2013) [Mp3 320kbps]",
     "age": "1523022136",
     "size": "124.37Mo",
     "completed": "182",
     "seed": "7",
     "leech": "0",
     "downloadurl": "https://www2.yggtorrent.ws//engine/download_torrent?id=223165"
    },
    {
     "url": "https://www2.yggtorrent.ws/torrent/audio/musique/268283-lomepal+flip+2017mpeg320kbps32bits44100hz",
     "name": "Lomepal.Flip.[2017][MPEG][320Kbps][32bits][44100Hz]",
     "age": "1529709191",
     "size": "147.25Mo",
     "completed": "175",
     "seed": "6",
     "leech": "0",
     "downloadurl": "https://www2.yggtorrent.ws//engine/download_torrent?id=268283"
    },
    {
     "url": "https://www2.yggtorrent.ws/torrent/audio/musique/318260-lomepal+-+cette+foutue+perle+2013mp3320kbps",
     "name": "Lomepal - Cette Foutue Perle [2013][MP3][320KBPS]",
     "age": "1537709507",
     "size": "70.91Mo",
     "completed": "205",
     "seed": "5",
     "leech": "0",
     "downloadurl": "https://www2.yggtorrent.ws//engine/download_torrent?id=318260"
    },
    {
     "url": "https://www2.yggtorrent.ws/torrent/audio/musique/496971-2014+lomepal+-+seigneur+mp3+320kbps",
     "name": "[2014] Lomepal - Seigneur [MP3 320kbps]",
     "age": "1567652957",
     "size": "84.18Mo",
     "completed": "133",
     "seed": "5",
     "leech": "0",
     "downloadurl": "https://www2.yggtorrent.ws//engine/download_torrent?id=496971"
    },
    {
     "url": "https://www2.yggtorrent.ws/torrent/audio/musique/376364-lomepal+caballero+keroué+vidji+-+fixpen+singe+2014flac+16bit44100hz",
     "name": "Lomepal / Caballero / Keroué / Vidji - Fixpen Singe [2014][FLAC 16Bit][44100Hz]",
     "age": "1545768641",
     "size": "129.19Mo",
     "completed": "88",
     "seed": "4",
     "leech": "0",
     "downloadurl": "https://www2.yggtorrent.ws//engine/download_torrent?id=376364"
    },
    {
     "url": "https://www2.yggtorrent.ws/torrent/audio/musique/314231-walter+lomepal+-+22h+6h+mastering+-+2012+mp3+320kb",
     "name": "Walter & Lomepal - 22H 6H Mastering - 2012 [MP3 320Kb]",
     "age": "1537089982",
     "size": "118.36Mo",
     "completed": "70",
     "seed": "2",
     "leech": "0",
     "downloadurl": "https://www2.yggtorrent.ws//engine/download_torrent?id=314231"
    },
    {
     "url": "https://www2.yggtorrent.ws/torrent/audio/musique/366236-lomepal+majesté+mp3+320+kbps",
     "name": "Lomepal Majesté  MP3 320 kbps",
     "age": "1544374741",
     "size": "50.62Mo",
     "completed": "197",
     "seed": "2",
     "leech": "0",
     "downloadurl": "https://www2.yggtorrent.ws//engine/download_torrent?id=366236"
    }
   ]